immGen.v
`timescale 1ns / 1ps

module immGen (
    input  wire [31:0] inst,     // 32-bit instruction input
    output reg  [31:0] imm_out   // sign-extended immediate output
);

    // Extract opcode field (bits [6:0])
    wire [6:0] opcode;
    assign opcode = inst[6:0];

    always @(*) begin
        case (opcode)

            // -------------------------------
            // I-TYPE FORMAT
            // Used by: LOAD, OP-IMM, JALR
            // Immediate = bits [31:20], sign-extended
            // -------------------------------
            7'b0000011,   // LOAD instructions
            7'b0010011,   // Arithmetic immediate (ADDI, etc.)
            7'b1100111:   // JALR
                imm_out = { {20{inst[31]}}, inst[31:20] };

            // -------------------------------
            // S-TYPE FORMAT (STORE)
            // Immediate split across two fields:
            // [31:25] and [11:7]
            // -------------------------------
            7'b0100011:
                imm_out = { {20{inst[31]}},
                            inst[31:25],
                            inst[11:7] };

            // -------------------------------
            // B-TYPE FORMAT (BRANCH)
            // Immediate bits arranged as:
            // [12 | 10:5 | 4:1 | 11] << 1
            // Note: LSB is always 0 (implicit shift)
            // -------------------------------
            7'b1100011:
                imm_out = { {19{inst[31]}}, // sign extension
                            inst[31],       // imm[12]
                            inst[7],        // imm[11]
                            inst[30:25],    // imm[10:5]
                            inst[11:8],     // imm[4:1]
                            1'b0 };         // shift left by 1

            // -------------------------------
            // U-TYPE FORMAT (LUI, AUIPC)
            // Upper 20 bits used, lower 12 bits are zero
            // -------------------------------
            7'b0110111,   // LUI
            7'b0010111:   // AUIPC
                imm_out = { inst[31:12], 12'b0 };

            // -------------------------------
            // J-TYPE FORMAT (JAL)
            // Immediate layout:
            // [20 | 10:1 | 11 | 19:12] << 1
            // -------------------------------
            7'b1101111:
                imm_out = { {11{inst[31]}}, // sign extension
                            inst[31],       // imm[20]
                            inst[19:12],    // imm[19:12]
                            inst[20],       // imm[11]
                            inst[30:21],    // imm[10:1]
                            1'b0 };         // shift left by 1

            // -------------------------------
            // DEFAULT CASE
            // No valid immediate
            // -------------------------------
            default:
                imm_out = 32'b0;

        endcase
    end

endmodule

mux2.v
// ============================================================
//  mux2.v
//  2-to-1 multiplexer.
//  sel = 0  ?  Y = A   (PC + 4, sequential)
//  sel = 1  ?  Y = B   (branch target)
// ============================================================
module mux2 (

    input  wire [31:0] A,      // PC + 4
    input  wire [31:0] B,      // Branch target
    input  wire  sel,    // PCSrc control signal
    output wire [31:0] Y       // Next PC
);
    assign Y = sel ? B : A;
endmodule

branchAdder.v
// ============================================================
//  branchAdder.v
//  Computes PC + (sign-extended immediate << 1).
//
//  NOTE: The B-type immediate from immGen is already the
//  sign-extended 13-bit offset encoded in the instruction.
//  RV32I branches are PC-relative: target = PC + imm,
//  where imm bit[0] is always 0 (2-byte aligned).
//  immGen delivers this value directly, so NO extra shift
//  is needed here.  If your immGen outputs the raw 12-bit
//  field (bits [12:1] only, i.e. NOT pre-shifted), replace
//  the assign with:
//      assign Branch_Target = PC + (Imm << 1);
// ============================================================
module branchAdder (
    input  wire [31:0] PC,
    input  wire [31:0] Imm,          // sign-extended B-type immediate from immGen
    output wire [31:0] Branch_Target
);
    assign Branch_Target = PC + Imm;
endmodule

pcAdder.v
// ============================================================
//  pcAdder.v
//  Computes PC + 4 for sequential instruction fetch.
// ============================================================
module pcAdder (
    input  wire [31:0] PC,
    output wire [31:0] PC_Plus4 //JUST ADDER WHEN NON BRANCH 
);
    assign PC_Plus4 = PC + 32'd4;
endmodule

ProgramCounter.v
// ============================================================
//  ProgramCounter.v
//  PC register with synchronous reset.
//  Initial value set to 0 so simulation shows clean zeros
//  instead of X before the first clock edge.
// ============================================================
`timescale 1ns/1ps

module ProgramCounter (
    input  wire        clk,
    input  wire        reset,
    input  wire [31:0] PC_Next,
    output reg  [31:0] PC
);
    // initial block gives PC a known value at time 0
    // so combinational outputs (PC+4, branch target) are
    initial PC = 32'h00000000; //initial value

    always @(posedge clk) begin
        if (reset)
            PC <= 32'h00000000; //if reset then 0
        else
            PC <= PC_Next; //move on to pc next which can be either Pc+4 or branch target adddress
    end

endmodule

task1.v
`timescale 1ns / 1ps
module tb_Task1;
    reg clk;
    reg reset;
    initial clk = 0;
    always #5 clk = ~clk;   // 10 ns period -> 100 MHz
    wire [31:0] PC;
    wire [31:0] PC_Plus4;
    wire [31:0] Branch_Target;
    wire [31:0] PC_Next;
    reg  PCSrc;
    reg  [31:0] inst;
    wire [31:0] Imm;

    ProgramCounter uPC (
        .clk     (clk),
        .reset   (reset),
        .PC_Next (PC_Next),
        .PC      (PC)
    );
    pcAdder uPCAdder (
        .PC      (PC),
        .PC_Plus4(PC_Plus4)
    );
    branchAdder uBranchAdder (
        .PC            (PC),
        .Imm           (Imm),
        .Branch_Target (Branch_Target)
    );
    mux2 uMux (
        .A   (PC_Plus4),
        .B   (Branch_Target),
        .sel (PCSrc),
        .Y   (PC_Next)
    );
immGen uImmGen (
    .inst    (inst),
    .imm_out (Imm)   // corrected port name
);

    task check;
        input [31:0] actual;
        input [31:0] expected;
        input [127:0] label;
        begin
            if (actual === expected)
                $display("PASS  %s : got 0x%08h", label, actual);
            else
                $display("FAIL  %s : expected 0x%08h, got 0x%08h", label, expected, actual);
        end
    endtask

    initial begin
        reset  = 1;
        PCSrc  = 0;
        inst   = 32'b0;
        @(posedge clk); #1;
        reset  = 0;

        $display("\n--- Sequential PC increment (PCSrc = 0) ---");
        @(posedge clk); #1; $display("  PC = 0x%08h  (expected 0x%08h)", PC, 32'd4);
        @(posedge clk); #1; $display("  PC = 0x%08h  (expected 0x%08h)", PC, 32'd8);
        @(posedge clk); #1; $display("  PC = 0x%08h  (expected 0x%08h)", PC, 32'd12);
        @(posedge clk); #1; $display("  PC = 0x%08h  (expected 0x%08h)", PC, 32'd16);
        @(posedge clk); #1; $display("  PC = 0x%08h  (expected 0x%08h)", PC, 32'd20);
        check(PC, 32'd20, "PC after 5 increments");

        $display("\n--- Branch taken (PCSrc = 1) ---");
        inst  = {12'd8, 5'd0, 3'b000, 5'd0, 7'b0010011}; // ADDI imm=8
        PCSrc = 1;
        @(posedge clk); #1;
        $display("  PC = 0x%08h  branch_target was 0x%08h", PC, 32'd36);
        check(PC, 32'd36, "PC after branch (20 + 8)");
        PCSrc = 0;
        @(posedge clk); #1;
        check(PC, 32'd40, "PC sequential after branch");

        $display("\n--- Immediate Generation ---");
        inst = {12'hFFB, 5'd2, 3'b000, 5'd1, 7'b0010011}; #1;
        check(Imm, 32'hFFFFFFFB, "I-type imm (-5)");

        inst = {12'd100, 5'd4, 3'b000, 5'd3, 7'b0010011}; #1;
        check(Imm, 32'd100,      "I-type imm (+100)");

        inst = {12'd12, 5'd6, 3'b010, 5'd5, 7'b0000011}; #1;
        check(Imm, 32'd12,       "I-type LOAD imm (12)");

        inst = {7'h7F, 5'd7, 5'd8, 3'b010, 5'h1D, 7'b0100011}; #1;
        check(Imm, 32'hFFFFFFFD, "S-type imm (-3)");

        inst = {7'b0000000, 5'd9, 5'd10, 3'b010, 5'b10100, 7'b0100011}; #1;
        check(Imm, 32'd20,       "S-type imm (+20)");

        inst = {1'b0, 6'b000000, 5'd2, 5'd1, 3'b000, 4'b1000, 1'b0, 7'b1100011}; #1;
        check(Imm, 32'd16,       "B-type imm (+16)");

        inst = {1'b1, 6'b111111, 5'd2, 5'd1, 3'b001, 4'b1100, 1'b1, 7'b1100011}; #1;
        check(Imm, 32'hFFFFFFF8, "B-type imm (-8)");

        $display("\n--- Simulation complete ---\n");
        $finish;
    end

    initial begin
        $dumpfile("tb_Task1.vcd");
        $dumpvars(0, tb_Task1);
    end
endmodule

lab_11/lab_10.sim/sim_1/behav/xsim/tb_Task1.vcd
$date
   Thu Apr  2 21:00:49 2026
$end
$version
  2020.1
$end
$timescale
  1ps
$end
$scope module tb_Task1 $end
$var reg 1 ! clk $end
$var reg 1 " reset $end
$var wire 32 # PC [31:0] $end
$var wire 32 $ PC_Plus4 [31:0] $end
$var wire 32 % Branch_Target [31:0] $end
$var wire 32 & PC_Next [31:0] $end
$var reg 1 ' PCSrc $end
$var reg 32 ( inst [31:0] $end
$var wire 32 ) Imm [31:0] $end
$scope module uPC $end
$var wire 1 * clk $end
$var wire 1 + reset $end
$var wire 32 & PC_Next [31:0] $end
$var reg 32 , PC [31:0] $end
$upscope $end
$scope module uPCAdder $end
$var wire 32 # PC [31:0] $end
$var wire 32 $ PC_Plus4 [31:0] $end
$upscope $end
$scope module uBranchAdder $end
$var wire 32 # PC [31:0] $end
$var wire 32 ) Imm [31:0] $end
$var wire 32 % Branch_Target [31:0] $end
$upscope $end
$scope module uMux $end
$var wire 32 $ A [31:0] $end
$var wire 32 % B [31:0] $end
$var wire 1 - sel $end
$var wire 32 & Y [31:0] $end
$upscope $end
$scope module uImmGen $end
$var wire 32 . inst [31:0] $end
$var reg 32 / imm_out [31:0] $end
$var wire 7 0 opcode [6:0] $end
$upscope $end
$scope task check $end
$var reg 32 1 actual [31:0] $end
$var reg 32 2 expected [31:0] $end
$var reg 128 3 label [127:0] $end
$upscope $end
$upscope $end
$enddefinitions $end
#0
$dumpvars
0!
1"
b0 #
b100 $
b0 %
b100 &
0'
b0 (
b0 )
0*
1+
b0 ,
0-
b0 .
b0 /
b0 0
bx 1
bx 2
bx 3
$end
#5000
1!
1*
b0 ,
#6000
0"
0+
#10000
0!
0*
#15000
1!
b100 #
b1000 $
b100 %
b1000 &
1*
b100 ,
#20000
0!
0*
#25000
1!
b1000 #
b1100 $
b1000 %
b1100 &
1*
b1000 ,
#30000
0!
0*
#35000
1!
b1100 #
b10000 $
b1100 %
b10000 &
1*
b1100 ,
#40000
0!
0*
#45000
1!
b10000 #
b10100 $
b10000 %
b10100 &
1*
b10000 ,
#50000
0!
0*
#55000
1!
b10100 #
b11000 $
b10100 %
b11000 &
1*
b10100 ,
#56000
b11100 %
b11100 &
1'
b100000000000000000010011 (
b1000 )
1-
b100000000000000000010011 .
b1000 /
b10011 0
b10100 1
b10100 2
b1110100011001010111001000100000001101010010000001101001011011100110001101110010011001010110110101100101011011100111010001110011 3
#60000
0!
0*
#65000
1!
b11100 #
b100000 $
b100100 %
b100100 &
1*
b11100 ,
#66000
b100000 &
0'
0-
b11100 1
b100100 2
b100000011000100111001001100001011011100110001101101000001000000010100000110010001100000010000000101011001000000011100000101001 3
#70000
0!
0*
#75000
1!
b100000 #
b100100 $
b101000 %
b100100 &
1*
b100000 ,
#76000
b11011 %
b11111111101100010000000010010011 (
b11111111111111111111111111111011 )
b11111111101100010000000010010011 .
b11111111111111111111111111111011 /
b100000 1
b101000 2
b1101001011000010110110000100000011000010110011001110100011001010111001000100000011000100111001001100001011011100110001101101000 3
#77000
b10000100 %
b110010000100000000110010011 (
b1100100 )
b110010000100000000110010011 .
b1100100 /
b11111111111111111111111111111011 1
b11111111111111111111111111111011 2
b10010010010110101110100011110010111000001100101001000000110100101101101011011010010000000101000001011010011010100101001 3
#78000
b101100 %
b110000110010001010000011 (
b1100 )
b110000110010001010000011 .
b1100 /
b11 0
b1100100 1
b1100100 2
b101101011101000111100101110000011001010010000001101001011011010110110100100000001010000010101100110001001100000011000000101001 3
#79000
b11101 %
b11111110011101000010111010100011 (
b11111111111111111111111111111101 )
b11111110011101000010111010100011 .
b11111111111111111111111111111101 /
b100011 0
b1100 1
b1100 2
b1110000011001010010000001001100010011110100000101000100001000000110100101101101011011010010000000101000001100010011001000101001 3
#80000
0!
b110100 %
b100101010010101000100011 (
b10100 )
0*
b100101010010101000100011 .
b10100 /
b11111111111111111111111111111101 1
b11111111111111111111111111111101 2
b10100110010110101110100011110010111000001100101001000000110100101101101011011010010000000101000001011010011001100101001 3
#81000
b110000 %
b1000001000100001100011 (
b10000 )
b1000001000100001100011 .
b10000 /
b1100011 0
b10100 1
b10100 2
b1010011001011010111010001111001011100000110010100100000011010010110110101101101001000000010100000101011001100100011000000101001 3
#82000
b11000 %
b11111110001000001001110011100011 (
b11111111111111111111111111111000 )
b11111110001000001001110011100011 .
b11111111111111111111111111111000 /
b10000 1
b10000 2
b1000010001011010111010001111001011100000110010100100000011010010110110101101101001000000010100000101011001100010011011000101001 3
#83000
b11111111111111111111111111111000 1
b11111111111111111111111111111000 2
b10000100010110101110100011110010111000001100101001000000110100101101101011011010010000000101000001011010011100000101001 3
